Workbook

Sheet ingredients_clean
A1: ing_id | B1: ing_name | C1: ing_weight | D1: ing_meas | E1: ing_price | F1: cost_per_unit
A2: ING001 | B2: Espresso beans | C2: 1000 | D2: grams | E2: 12 | F2: =E2/C2 -> 0.012
A3: ING002 | B3: Whole Milk | C3: 1000 | D3: ml | E3: 1.2 | F3: =E3/C3 -> 0.0012
A4: ING003 | B4: Cheddar | C4: 500 | D4: grams | E4: 7.45 | F4: =E4/C4 -> 0.0149
A5: ING004 | B5: Mozzarella | C5: 500 | D5: grams | E5: 5 | F5: =E5/C5 -> 0.01
A6: ING005 | B6: Whipped cream | C6: 300 | D6: ml | E6: 1.35 | F6: =E6/C6 -> 0.0045
A7: ING006 | B7: Vanilla syrup | C7: 1000 | D7: ml | E7: 14.52 | F7: =E7/C7 -> 0.01452
A8: ING007 | B8: Barista chocolate syrup | C8: 1000 | D8: ml | E8: 8.49 | F8: =E8/C8 -> 0.00849
A9: ING008 | B9: Barista white chocolate syrup | C9: 1000 | D9: ml | E9: 8.49 | F9: =E9/C9 -> 0.00849
A10: ING009 | B10: Barista caramel sauce | C10: 1000 | D10: ml | E10: 8.49 | F10: =E10/C10 -> 0.00849
A11: ING010 | B11: Sugar | C11: 1000 | D11: grams | E11: 1.5 | F11: =E11/C11 -> 0.0015
A12: ING011 | B12: Panini Bread | C12: 4 | D12: units | E12: 1.35 | F12: =E12/C12 -> 0.3375
A13: ING012 | B13: Cocoa powder | C13: 1000 | D13: grams | E13: 22 | F13: =E13/C13 -> 0.022
... A19: ING018 | B19: Vanilla extract | C19: 60 | D19: ml | E19: 9.99 | F19: =E19/C19 -> 0.1665

Sheet recipe_clean
A1: row_id | B1: recipe_id | C1: ing_id | D1: quantity | E1: recipe_ing_key | F1: dup_count
A2: 1 | B2: HDR-CAP-MD | C2: ING001 | D2: 8 | E2: =B2 & "|" & C2 -> HDR-CAP-MD|ING001 | F2: =COUNTIF($E:$E, E2) -> 1
A3: 2 | B3: HDR-CAP-MD | C3: ING002 | D3: 130 | E3: =B3 & "|" & C3 -> HDR-CAP-MD|ING002 | F3: =COUNTIF($E:$E, E3) -> 1
A4: 3 | B4: HDR-CAP-LG | C4: ING001 | D4: 10 | E4: =B4 & "|" & C4 -> HDR-CAP-LG|ING001 | F4: =COUNTIF($E:$E, E4) -> 1
A5: 4 | B5: HDR-CAP-LG | C5: ING002 | D5: 180 | E5: =B5 & "|" & C5 -> HDR-CAP-LG|ING002 | F5: =COUNTIF($E:$E, E5) -> 1
A6: 5 | B6: HDR-LAT-MD | C6: ING001 | D6: 8 | E6: =B6 & "|" & C6 -> HDR-LAT-MD|ING001 | F6: =COUNTIF($E:$E, E6) -> 1
A7: 6 | B7: HDR-LAT-MD | C7: ING002 | D7: 130 | E7: =B7 & "|" & C7 -> HDR-LAT-MD|ING002 | F7: =COUNTIF($E:$E, E7) -> 1
A8: 7 | B8: HDR-LAT-LG | C8: ING001 | D8: 10 | E8: =B8 & "|" & C8 -> HDR-LAT-LG|ING001 | F8: =COUNTIF($E:$E, E8) -> 1
A9: 8 | B9: HDR-LAT-LG | C9: ING002 | D9: 180 | E9: =B9 & "|" & C9 -> HDR-LAT-LG|ING002 | F9: =COUNTIF($E:$E, E9) -> 1
A10: 9 | B10: HDR-FLT | C10: ING001 | D10: 8 | E10: =B10 & "|" & C10 -> HDR-FLT|ING001 | F10: =COUNTIF($E:$E, E10) -> 1
A11: 10 | B11: HDR-FLT | C11: ING002 | D11: 160 | E11: =B11 & "|" & C11 -> HDR-FLT|ING002 | F11: =COUNTIF($E:$E, E11) -> 1
A12: 11 | B12: HDR-CRM-MD | C12: ING001 | D12: 8 | E12: =B12 & "|" & C12 -> HDR-CRM-MD|ING001 | F12: =COUNTIF($E:$E, E12) -> 1
A13: 12 | B13: HDR-CRM-MD | C13: ING002 | D13: 120 | E13: =B13 & "|" & C13 -> HDR-CRM-MD|ING002 | F13: =COUNTIF($E:$E, E13) -> 1
... A62: 61 | B62: SNK-SSM | C62: ING004 | D62: 20 | E62: =B62 & "|" & C62 -> SNK-SSM|ING004 | F62: =COUNTIF($E:$E, E62) -> 1

Sheet inventory_clean
A1: inv_id | B1: ing_id | C1: quantity
A2: inv001 | B2: ING001 | C2: 4
A3: inv002 | B3: ING002 | C3: 55
A4: inv003 | B4: ING003 | C4: 1
A5: inv004 | B5: ING004 | C5: 4
A6: inv005 | B6: ING005 | C6: 7
A7: inv006 | B7: ING006 | C7: 3
A8: inv007 | B8: ING007 | C8: 3
A9: inv008 | B9: ING008 | C9: 4
A10: inv009 | B10: ING009 | C10: 1
A11: inv010 | B11: ING010 | C11: 4
A12: inv011 | B12: ING011 | C12: 20
A13: inv012 | B13: ING012 | C13: 5
... A19: inv018 | B19: ING018 | C19: 2

Sheet items_clean
A1: item_id | B1: sku | C1: item_name | D1: item_cat | E1: item_size | F1: item_price
A2: It001 | B2: HDR-CAP-MD | C2: Cappuccino | D2: Hot Drinks | E2: Medium | F2: 3.45
A3: It002 | B3: HDR-CAP-LG | C3: Cappuccino | D3: Hot Drinks | E3: Large | F3: 3.75
A4: It003 | B4: HDR-LAT-MD | C4: Latte | D4: Hot Drinks | E4: Medium | F4: 3.45
A5: It004 | B5: HDR-LAT-LG | C5: Latte | D5: Hot Drinks | E5: Large | F5: 3.75
A6: It005 | B6: HDR-FLT | C6: Flat White | D6: Hot Drinks | E6: N/A | F6: 3.15
A7: It006 | B7: HDR-CRM-MD | C7: Caramel Macchiato | D7: Hot Drinks | E7: Medium | F7: 4.2
A8: It007 | B8: HDR-CRM-LG | C8: Caramel Macchiato | D8: Hot Drinks | E8: Large | F8: 4.6
A9: It008 | B9: HDR-ESP | C9: Espresso | D9: Hot Drinks | E9: N/A | F9: 2.15
A10: It009 | B10: HDR-MOC-MD | C10: Mocha | D10: Hot Drinks | E10: Medium | F10: 4
A11: It010 | B11: HDR-MOC-LG | C11: Mocha | D11: Hot Drinks | E11: Large | F11: 4.6
A12: It011 | B12: HDR-WMO-MD | C12: White Mocha | D12: Hot Drinks | E12: Medium | F12: 4.5
A13: It012 | B13: HDR-WMO-LG | C13: White Mocha | D13: Hot Drinks | E13: Large | F13: 4.7
... A25: It024 | B25: SNK-SSM | C25: Sandwich Salami&Mozzarella | D25: Snacks | E25: N/A | F25: 5.5

Sheet orders_clean
A1: row_id | B1: order_id | C1: created_at | D1: item_id | E1: quantity | F1: cust_name | G1: in_or_out | H1: item_master_match | I1: item_valid_flag
A2: 1 | B2: ORD001 | C2: 45334.295 | D2: It008 | E2: 1 | F2: Alex | G2: out | H2: =IF(COUNTIF(items_clean!$A:$A, D2)>0, "Valid", "Invalid") -> Valid | I2: =IF(COUNTIF(items_clean!$A:$A, D2)>0, 1, 0) -> 1
A3: 2 | B3: ORD002 | C3: 45334.298 | D3: It014 | E3: 1 | F3: Jordan | G3: in | H3: =IF(COUNTIF(items_clean!$A:$A, D3)>0, "Valid", "Invalid") -> Valid | I3: =IF(COUNTIF(items_clean!$A:$A, D3)>0, 1, 0) -> 1
A4: 3 | B4: ORD003 | C4: 45334.302 | D4: It008 | E4: 1 | F4: Taylor | G4: out | H4: =IF(COUNTIF(items_clean!$A:$A, D4)>0, "Valid", "Invalid") -> Valid | I4: =IF(COUNTIF(items_clean!$A:$A, D4)>0, 1, 0) -> 1
A5: 4 | B5: ORD004 | C5: 45334.305 | D5: It019 | E5: 1 | F5: Casey | G5: out | H5: =IF(COUNTIF(items_clean!$A:$A, D5)>0, "Valid", "Invalid") -> Valid | I5: =IF(COUNTIF(items_clean!$A:$A, D5)>0, 1, 0) -> 1
A6: 5 | B6: ORD005 | C6: 45334.308 | D6: It024 | E6: 1 | F6: Jamie | G6: out | H6: =IF(COUNTIF(items_clean!$A:$A, D6)>0, "Valid", "Invalid") -> Valid | I6: =IF(COUNTIF(items_clean!$A:$A, D6)>0, 1, 0) -> 1
A7: 6 | B7: ORD006 | C7: 45334.311 | D7: It001 | E7: 1 | F7: Morgan | G7: in | H7: =IF(COUNTIF(items_clean!$A:$A, D7)>0, "Valid", "Invalid") -> Valid | I7: =IF(COUNTIF(items_clean!$A:$A, D7)>0, 1, 0) -> 1
A8: 7 | B8: ORD006 | C8: 45334.311 | D8: It016 | E8: 1 | F8: Morgan | G8: in | H8: =IF(COUNTIF(items_clean!$A:$A, D8)>0, "Valid", "Invalid") -> Valid | I8: =IF(COUNTIF(items_clean!$A:$A, D8)>0, 1, 0) -> 1
A9: 8 | B9: ORD007 | C9: 45334.315 | D9: It005 | E9: 1 | F9: Riley | G9: out | H9: =IF(COUNTIF(items_clean!$A:$A, D9)>0, "Valid", "Invalid") -> Valid | I9: =IF(COUNTIF(items_clean!$A:$A, D9)>0, 1, 0) -> 1
A10: 9 | B10: ORD007 | C10: 45334.315 | D10: It020 | E10: 1 | F10: Riley | G10: Unknown | H10: =IF(COUNTIF(items_clean!$A:$A, D10)>0, "Valid", "Invalid") -> Valid | I10: =IF(COUNTIF(items_clean!$A:$A, D10)>0, 1, 0) -> 1
A11: 10 | B11: ORD008 | C11: 45334.319 | D11: It006 | E11: 1 | F11: Cameron | G11: in | H11: =IF(COUNTIF(items_clean!$A:$A, D11)>0, "Valid", "Invalid") -> Valid | I11: =IF(COUNTIF(items_clean!$A:$A, D11)>0, 1, 0) -> 1
A12: 11 | B12: ORD008 | C12: 45334.319 | D12: It018 | E12: 1 | F12: Cameron | G12: Unknown | H12: =IF(COUNTIF(items_clean!$A:$A, D12)>0, "Valid", "Invalid") -> Valid | I12: =IF(COUNTIF(items_clean!$A:$A, D12)>0, 1, 0) -> 1
A13: 12 | B13: ORD009 | C13: 45334.322 | D13: It023 | E13: 1 | F13: Quinn | G13: out | H13: =IF(COUNTIF(items_clean!$A:$A, D13)>0, "Valid", "Invalid") -> Valid | I13: =IF(COUNTIF(items_clean!$A:$A, D13)>0, 1, 0) -> 1
... A521: 520 | B521: ORD437 | C521: 45339.708 | D521: It026 | E521: 1 | F521: Kiera | G521: in | H521: =IF(COUNTIF(items_clean!$A:$A, D521)>0, "Valid", "Invalid") -> Invalid | I521: =IF(COUNTIF(items_clean!$A:$A, D521)>0, 1, 0) -> 0

Sheet rota_clean
A1: row_id | B1: rota_id | C1: date | D1: shift_id | E1: staff_id
A2: 1 | B2: RT001 | C2: 45334 | D2: SH001 | E2: ST001
A3: 2 | B3: RT001 | C3: 45334 | D3: SH001 | E3: ST003
A4: 3 | B4: RT001 | C4: 45334 | D4: SH002 | E4: ST001
A5: 4 | B5: RT002 | C5: 45335 | D5: SH003 | E5: ST002
A6: 5 | B6: RT002 | C6: 45335 | D6: SH003 | E6: ST004
A7: 6 | B7: RT002 | C7: 45335 | D7: SH004 | E7: ST002
A8: 7 | B8: RT003 | C8: 45336 | D8: SH005 | E8: ST001
A9: 8 | B9: RT003 | C9: 45336 | D9: SH005 | E9: ST003
A10: 9 | B10: RT003 | C10: 45336 | D10: SH006 | E10: ST003
A11: 10 | B11: RT004 | C11: 45337 | D11: SH007 | E11: ST002
A12: 11 | B12: RT004 | C12: 45337 | D12: SH007 | E12: ST004
A13: 12 | B13: RT004 | C13: 45337 | D13: SH008 | E13: ST004
... A19: 18 | B19: RT006 | C19: 45339 | D19: SH012 | E19: ST004

Sheet shift_clean
A1: shift_id | B1: day_of_week | C1: day_number | D1: start_time | E1: end_time
A2: SH001 | B2: Monday | C2: 1 | D2: 0.29166667 | E2: 0.54166667
A3: SH002 | B3: Monday | C3: 1 | D3: 0.54166667 | E3: 0.70833333
A4: SH003 | B4: Tuesday | C4: 2 | D4: 0.29166667 | E4: 0.54166667
A5: SH004 | B5: Tuesday | C5: 2 | D5: 0.54166667 | E5: 0.70833333
A6: SH005 | B6: Wednesday | C6: 3 | D6: 0.29166667 | E6: 0.54166667
A7: SH006 | B7: Wednesday | C7: 3 | D7: 0.54166667 | E7: 0.70833333
A8: SH007 | B8: Thursday | C8: 4 | D8: 0.29166667 | E8: 0.54166667
A9: SH008 | B9: Thursday | C9: 4 | D9: 0.54166667 | E9: 0.70833333
A10: SH009 | B10: Friday | C10: 5 | D10: 0.29166667 | E10: 0.54166667
A11: SH010 | B11: Friday | C11: 5 | D11: 0.54166667 | E11: 0.70833333
A12: SH011 | B12: Saturday | C12: 6 | D12: 0.29166667 | E12: 0.54166667
A13: SH012 | B13: Saturday | C13: 6 | D13: 0.54166667 | E13: 0.70833333

Sheet staff_clean
A1: staff_id | B1: first_name | C1: last_name | D1: position | E1: sal_per_hour
A2: ST001 | B2: Emma | C2: Johnson | D2: Barista | E2: 10
A3: ST002 | B3: Liam | C3: Smith | D3: Barista | E3: 10
A4: ST003 | B4: Olivia | C4: Williams | D4: Barista | E4: 10
A5: ST004 | B5: Noah | C5: Brown | D5: Barista | E5: 10

Sheet item_ing_cost_bridge
A1: row_id | B1: recipe_id | C1: ing_id | D1: quantity | E1: cost_per_unit | F1: ingredient_cost
A2: 1 | B2: HDR-CAP-MD | C2: ING001 | D2: 8 | E2: =_xlfn.XLOOKUP(C2, ingredients_clean!A:A, ingredients_clean!F:F, "") -> 0.012 | F2: =D2*E2 -> 0.096
A3: 2 | B3: HDR-CAP-MD | C3: ING002 | D3: 130 | E3: =_xlfn.XLOOKUP(C3, ingredients_clean!A:A, ingredients_clean!F:F, "") -> 0.0012 | F3: =D3*E3 -> 0.156
A4: 3 | B4: HDR-CAP-LG | C4: ING001 | D4: 10 | E4: =_xlfn.XLOOKUP(C4, ingredients_clean!A:A, ingredients_clean!F:F, "") -> 0.012 | F4: =D4*E4 -> 0.12
A5: 4 | B5: HDR-CAP-LG | C5: ING002 | D5: 180 | E5: =_xlfn.XLOOKUP(C5, ingredients_clean!A:A, ingredients_clean!F:F, "") -> 0.0012 | F5: =D5*E5 -> 0.216
A6: 5 | B6: HDR-LAT-MD | C6: ING001 | D6: 8 | E6: =_xlfn.XLOOKUP(C6, ingredients_clean!A:A, ingredients_clean!F:F, "") -> 0.012 | F6: =D6*E6 -> 0.096
A7: 6 | B7: HDR-LAT-MD | C7: ING002 | D7: 130 | E7: =_xlfn.XLOOKUP(C7, ingredients_clean!A:A, ingredients_clean!F:F, "") -> 0.0012 | F7: =D7*E7 -> 0.156
A8: 7 | B8: HDR-LAT-LG | C8: ING001 | D8: 10 | E8: =_xlfn.XLOOKUP(C8, ingredients_clean!A:A, ingredients_clean!F:F, "") -> 0.012 | F8: =D8*E8 -> 0.12
A9: 8 | B9: HDR-LAT-LG | C9: ING002 | D9: 180 | E9: =_xlfn.XLOOKUP(C9, ingredients_clean!A:A, ingredients_clean!F:F, "") -> 0.0012 | F9: =D9*E9 -> 0.216
A10: 9 | B10: HDR-FLT | C10: ING001 | D10: 8 | E10: =_xlfn.XLOOKUP(C10, ingredients_clean!A:A, ingredients_clean!F:F, "") -> 0.012 | F10: =D10*E10 -> 0.096
A11: 10 | B11: HDR-FLT | C11: ING002 | D11: 160 | E11: =_xlfn.XLOOKUP(C11, ingredients_clean!A:A, ingredients_clean!F:F, "") -> 0.0012 | F11: =D11*E11 -> 0.192
A12: 11 | B12: HDR-CRM-MD | C12: ING001 | D12: 8 | E12: =_xlfn.XLOOKUP(C12, ingredients_clean!A:A, ingredients_clean!F:F, "") -> 0.012 | F12: =D12*E12 -> 0.096
A13: 12 | B13: HDR-CRM-MD | C13: ING002 | D13: 120 | E13: =_xlfn.XLOOKUP(C13, ingredients_clean!A:A, ingredients_clean!F:F, "") -> 0.0012 | F13: =D13*E13 -> 0.144
... A62: 61 | B62: SNK-SSM | C62: ING004 | D62: 20 | E62: =_xlfn.XLOOKUP(C62, ingredients_clean!A:A, ingredients_clean!F:F, "") -> 0.01 | F62: =D62*E62 -> 0.2

Sheet recipe_cost
A1: recipe_id | B1: total_recipe_cost
A2: CDR-CCF-LG | B2: 0.336
A3: CDR-CCF-MD | B3: 0.252
A4: CDR-CMO-LG | B4: 0.5667
A5: CDR-CMO-MD | B5: 0.4098
A6: CDR-ICT-LG | B6: 0.26985
A7: CDR-ICT-MD | B7: 0.19
A8: CDR-LMN-LG | B8: 0.36
A9: CDR-LMN-MD | B9: 0.345
A10: HDR-CAP-LG | B10: 0.336
A11: HDR-CAP-MD | B11: 0.252
A12: HDR-CRM-LG | B12: 0.5667
A13: HDR-CRM-MD | B13: 0.4098
... A25: SNK-SSM | B25: 1.312

Sheet sales_enriched
A1: row_id | B1: order_id | C1: created_at | D1: order_date | E1: order_hour | F1: shift_bucket | G1: day_of_week | H1: cust_name | I1: in_or_out | J1: item_id | K1: sku | L1: item_name | M1: item_cat | N1: item_size | O1: quantity | P1: item_price | Q1: revenue | R1: unit_cost | S1: total_cost | T1: contribution | U1: margin_pct
A2: 1 | B2: ORD001 | C2: 45334.295 | D2: =INT(C2) -> 45334 | E2: =HOUR(C2) -> 7 | F2: {=_xlfn.IFS( E2<11,"Morning", E2<15,"Afternoon", TRUE,"Evening" )} -> Morning | G2: =TEXT(C2,"ddd") -> Mon | H2: Alex | I2: out | J2: It008 | K2: =_xlfn.XLOOKUP($J2, items_clean!$A:$A, items_clean!$B:$B, "") -> HDR-ESP | L2: =_xlfn.XLOOKUP($J2, items_clean!$A:$A, items_clean!$C:$C, "") -> Espresso | M2: =_xlfn.XLOOKUP($J2, items_clean!$A:$A, items_clean!$D:$D, "") -> Hot Drinks | N2: =_xlfn.XLOOKUP($J2, items_clean!$A:$A, items_clean!$E:$E, "") -> N/A | O2: 1 | P2: =_xlfn.XLOOKUP($J2, items_clean!$A:$A, items_clean!$F:$F, "") -> 2.15 | Q2: =O2*P2 -> 2.15 | R2: =_xlfn.XLOOKUP(K2, recipe_cost!$A:$A, recipe_cost!$B:$B, "") -> 0.096 | S2: =O2 * R2 -> 0.096 | T2: =Q2-S2 -> 2.054 | U2: =IF(Q2=0,"",T2/Q2) -> 0.95534884
A3: 2 | B3: ORD002 | C3: 45334.298 | D3: =INT(C3) -> 45334 | E3: =HOUR(C3) -> 7 | F3: {=_xlfn.IFS( E3<11,"Morning", E3<15,"Afternoon", TRUE,"Evening" )} -> Morning | G3: =TEXT(C3,"ddd") -> Mon | H3: Jordan | I3: in | J3: It014 | K3: =_xlfn.XLOOKUP($J3, items_clean!$A:$A, items_clean!$B:$B, "") -> HDR-HCH-LG | L3: =_xlfn.XLOOKUP($J3, items_clean!$A:$A, items_clean!$C:$C, "") -> Hot Chocolate | M3: =_xlfn.XLOOKUP($J3, items_clean!$A:$A, items_clean!$D:$D, "") -> Hot Drinks | N3: =_xlfn.XLOOKUP($J3, items_clean!$A:$A, items_clean!$E:$E, "") -> Large | O3: 1 | P3: =_xlfn.XLOOKUP($J3, items_clean!$A:$A, items_clean!$F:$F, "") -> 4.6 | Q3: =O3*P3 -> 4.6 | R3: =_xlfn.XLOOKUP(K3, recipe_cost!$A:$A, recipe_cost!$B:$B, "") -> 1.481 | S3: =O3 * R3 -> 1.481 | T3: =Q3-S3 -> 3.119 | U3: =IF(Q3=0,"",T3/Q3) -> 0.67804348
A4: 3 | B4: ORD003 | C4: 45334.302 | D4: =INT(C4) -> 45334 | E4: =HOUR(C4) -> 7 | F4: {=_xlfn.IFS( E4<11,"Morning", E4<15,"Afternoon", TRUE,"Evening" )} -> Morning | G4: =TEXT(C4,"ddd") -> Mon | H4: Taylor | I4: out | J4: It008 | K4: =_xlfn.XLOOKUP($J4, items_clean!$A:$A, items_clean!$B:$B, "") -> HDR-ESP | L4: =_xlfn.XLOOKUP($J4, items_clean!$A:$A, items_clean!$C:$C, "") -> Espresso | M4: =_xlfn.XLOOKUP($J4, items_clean!$A:$A, items_clean!$D:$D, "") -> Hot Drinks | N4: =_xlfn.XLOOKUP($J4, items_clean!$A:$A, items_clean!$E:$E, "") -> N/A | O4: 1 | P4: =_xlfn.XLOOKUP($J4, items_clean!$A:$A, items_clean!$F:$F, "") -> 2.15 | Q4: =O4*P4 -> 2.15 | R4: =_xlfn.XLOOKUP(K4, recipe_cost!$A:$A, recipe_cost!$B:$B, "") -> 0.096 | S4: =O4 * R4 -> 0.096 | T4: =Q4-S4 -> 2.054 | U4: =IF(Q4=0,"",T4/Q4) -> 0.95534884
A5: 4 | B5: ORD004 | C5: 45334.305 | D5: =INT(C5) -> 45334 | E5: =HOUR(C5) -> 7 | F5: {=_xlfn.IFS( E5<11,"Morning", E5<15,"Afternoon", TRUE,"Evening" )} -> Morning | G5: =TEXT(C5,"ddd") -> Mon | H5: Casey | I5: out | J5: It019 | K5: =_xlfn.XLOOKUP($J5, items_clean!$A:$A, items_clean!$B:$B, "") -> CDR-ICT-MD | L5: =_xlfn.XLOOKUP($J5, items_clean!$A:$A, items_clean!$C:$C, "") -> Iced Tea | M5: =_xlfn.XLOOKUP($J5, items_clean!$A:$A, items_clean!$D:$D, "") -> Cold Drinks | N5: =_xlfn.XLOOKUP($J5, items_clean!$A:$A, items_clean!$E:$E, "") -> Medium | O5: 1 | P5: =_xlfn.XLOOKUP($J5, items_clean!$A:$A, items_clean!$F:$F, "") -> 3.25 | Q5: =O5*P5 -> 3.25 | R5: =_xlfn.XLOOKUP(K5, recipe_cost!$A:$A, recipe_cost!$B:$B, "") -> 0.19 | S5: =O5 * R5 -> 0.19 | T5: =Q5-S5 -> 3.06 | U5: =IF(Q5=0,"",T5/Q5) -> 0.94153846
A6: 5 | B6: ORD005 | C6: 45334.308 | D6: =INT(C6) -> 45334 | E6: =HOUR(C6) -> 7 | F6: {=_xlfn.IFS( E6<11,"Morning", E6<15,"Afternoon", TRUE,"Evening" )} -> Morning | G6: =TEXT(C6,"ddd") -> Mon | H6: Jamie | I6: out | J6: It024 | K6: =_xlfn.XLOOKUP($J6, items_clean!$A:$A, items_clean!$B:$B, "") -> SNK-SSM | L6: =_xlfn.XLOOKUP($J6, items_clean!$A:$A, items_clean!$C:$C, "") -> Sandwich Salami&Mozzarella | M6: =_xlfn.XLOOKUP($J6, items_clean!$A:$A, items_clean!$D:$D, "") -> Snacks | N6: =_xlfn.XLOOKUP($J6, items_clean!$A:$A, items_clean!$E:$E, "") -> N/A | O6: 1 | P6: =_xlfn.XLOOKUP($J6, items_clean!$A:$A, items_clean!$F:$F, "") -> 5.5 | Q6: =O6*P6 -> 5.5 | R6: =_xlfn.XLOOKUP(K6, recipe_cost!$A:$A, recipe_cost!$B:$B, "") -> 1.312 | S6: =O6 * R6 -> 1.312 | T6: =Q6-S6 -> 4.188 | U6: =IF(Q6=0,"",T6/Q6) -> 0.76145455
A7: 6 | B7: ORD006 | C7: 45334.311 | D7: =INT(C7) -> 45334 | E7: =HOUR(C7) -> 7 | F7: {=_xlfn.IFS( E7<11,"Morning", E7<15,"Afternoon", TRUE,"Evening" )} -> Morning | G7: =TEXT(C7,"ddd") -> Mon | H7: Morgan | I7: in | J7: It001 | K7: =_xlfn.XLOOKUP($J7, items_clean!$A:$A, items_clean!$B:$B, "") -> HDR-CAP-MD | L7: =_xlfn.XLOOKUP($J7, items_clean!$A:$A, items_clean!$C:$C, "") -> Cappuccino | M7: =_xlfn.XLOOKUP($J7, items_clean!$A:$A, items_clean!$D:$D, "") -> Hot Drinks | N7: =_xlfn.XLOOKUP($J7, items_clean!$A:$A, items_clean!$E:$E, "") -> Medium | O7: 1 | P7: =_xlfn.XLOOKUP($J7, items_clean!$A:$A, items_clean!$F:$F, "") -> 3.45 | Q7: =O7*P7 -> 3.45 | R7: =_xlfn.XLOOKUP(K7, recipe_cost!$A:$A, recipe_cost!$B:$B, "") -> 0.252 | S7: =O7 * R7 -> 0.252 | T7: =Q7-S7 -> 3.198 | U7: =IF(Q7=0,"",T7/Q7) -> 0.92695652
A8: 7 | B8: ORD006 | C8: 45334.311 | D8: =INT(C8) -> 45334 | E8: =HOUR(C8) -> 7 | F8: {=_xlfn.IFS( E8<11,"Morning", E8<15,"Afternoon", TRUE,"Evening" )} -> Morning | G8: =TEXT(C8,"ddd") -> Mon | H8: Morgan | I8: in | J8: It016 | K8: =_xlfn.XLOOKUP($J8, items_clean!$A:$A, items_clean!$B:$B, "") -> CDR-CCF-LG | L8: =_xlfn.XLOOKUP($J8, items_clean!$A:$A, items_clean!$C:$C, "") -> Cold Coffee | M8: =_xlfn.XLOOKUP($J8, items_clean!$A:$A, items_clean!$D:$D, "") -> Cold Drinks | N8: =_xlfn.XLOOKUP($J8, items_clean!$A:$A, items_clean!$E:$E, "") -> Large | O8: 1 | P8: =_xlfn.XLOOKUP($J8, items_clean!$A:$A, items_clean!$F:$F, "") -> 3.75 | Q8: =O8*P8 -> 3.75 | R8: =_xlfn.XLOOKUP(K8, recipe_cost!$A:$A, recipe_cost!$B:$B, "") -> 0.336 | S8: =O8 * R8 -> 0.336 | T8: =Q8-S8 -> 3.414 | U8: =IF(Q8=0,"",T8/Q8) -> 0.9104
A9: 8 | B9: ORD007 | C9: 45334.315 | D9: =INT(C9) -> 45334 | E9: =HOUR(C9) -> 7 | F9: {=_xlfn.IFS( E9<11,"Morning", E9<15,"Afternoon", TRUE,"Evening" )} -> Morning | G9: =TEXT(C9,"ddd") -> Mon | H9: Riley | I9: out | J9: It005 | K9: =_xlfn.XLOOKUP($J9, items_clean!$A:$A, items_clean!$B:$B, "") -> HDR-FLT | L9: =_xlfn.XLOOKUP($J9, items_clean!$A:$A, items_clean!$C:$C, "") -> Flat White | M9: =_xlfn.XLOOKUP($J9, items_clean!$A:$A, items_clean!$D:$D, "") -> Hot Drinks | N9: =_xlfn.XLOOKUP($J9, items_clean!$A:$A, items_clean!$E:$E, "") -> N/A | O9: 1 | P9: =_xlfn.XLOOKUP($J9, items_clean!$A:$A, items_clean!$F:$F, "") -> 3.15 | Q9: =O9*P9 -> 3.15 | R9: =_xlfn.XLOOKUP(K9, recipe_cost!$A:$A, recipe_cost!$B:$B, "") -> 0.288 | S9: =O9 * R9 -> 0.288 | T9: =Q9-S9 -> 2.862 | U9: =IF(Q9=0,"",T9/Q9) -> 0.90857143
A10: 9 | B10: ORD007 | C10: 45334.315 | D10: =INT(C10) -> 45334 | E10: =HOUR(C10) -> 7 | F10: {=_xlfn.IFS( E10<11,"Morning", E10<15,"Afternoon", TRUE,"Evening" )} -> Morning | G10: =TEXT(C10,"ddd") -> Mon | H10: Riley | I10: Unknown | J10: It020 | K10: =_xlfn.XLOOKUP($J10, items_clean!$A:$A, items_clean!$B:$B, "") -> CDR-ICT-LG | L10: =_xlfn.XLOOKUP($J10, items_clean!$A:$A, items_clean!$C:$C, "") -> Iced Tea | M10: =_xlfn.XLOOKUP($J10, items_clean!$A:$A, items_clean!$D:$D, "") -> Cold Drinks | N10: =_xlfn.XLOOKUP($J10, items_clean!$A:$A, items_clean!$E:$E, "") -> Large | O10: 1 | P10: =_xlfn.XLOOKUP($J10, items_clean!$A:$A, items_clean!$F:$F, "") -> 3.55 | Q10: =O10*P10 -> 3.55 | R10: =_xlfn.XLOOKUP(K10, recipe_cost!$A:$A, recipe_cost!$B:$B, "") -> 0.26985 | S10: =O10 * R10 -> 0.26985 | T10: =Q10-S10 -> 3.28015 | U10: =IF(Q10=0,"",T10/Q10) -> 0.92398592
A11: 10 | B11: ORD008 | C11: 45334.319 | D11: =INT(C11) -> 45334 | E11: =HOUR(C11) -> 7 | F11: {=_xlfn.IFS( E11<11,"Morning", E11<15,"Afternoon", TRUE,"Evening" )} -> Morning | G11: =TEXT(C11,"ddd") -> Mon | H11: Cameron | I11: in | J11: It006 | K11: =_xlfn.XLOOKUP($J11, items_clean!$A:$A, items_clean!$B:$B, "") -> HDR-CRM-MD | L11: =_xlfn.XLOOKUP($J11, items_clean!$A:$A, items_clean!$C:$C, "") -> Caramel Macchiato | M11: =_xlfn.XLOOKUP($J11, items_clean!$A:$A, items_clean!$D:$D, "") -> Hot Drinks | N11: =_xlfn.XLOOKUP($J11, items_clean!$A:$A, items_clean!$E:$E, "") -> Medium | O11: 1 | P11: =_xlfn.XLOOKUP($J11, items_clean!$A:$A, items_clean!$F:$F, "") -> 4.2 | Q11: =O11*P11 -> 4.2 | R11: =_xlfn.XLOOKUP(K11, recipe_cost!$A:$A, recipe_cost!$B:$B, "") -> 0.4098 | S11: =O11 * R11 -> 0.4098 | T11: =Q11-S11 -> 3.7902 | U11: =IF(Q11=0,"",T11/Q11) -> 0.90242857
A12: 11 | B12: ORD008 | C12: 45334.319 | D12: =INT(C12) -> 45334 | E12: =HOUR(C12) -> 7 | F12: {=_xlfn.IFS( E12<11,"Morning", E12<15,"Afternoon", TRUE,"Evening" )} -> Morning | G12: =TEXT(C12,"ddd") -> Mon | H12: Cameron | I12: Unknown | J12: It018 | K12: =_xlfn.XLOOKUP($J12, items_clean!$A:$A, items_clean!$B:$B, "") -> CDR-CMO-LG | L12: =_xlfn.XLOOKUP($J12, items_clean!$A:$A, items_clean!$C:$C, "") -> Cold Mocha | M12: =_xlfn.XLOOKUP($J12, items_clean!$A:$A, items_clean!$D:$D, "") -> Cold Drinks | N12: =_xlfn.XLOOKUP($J12, items_clean!$A:$A, items_clean!$E:$E, "") -> Large | O12: 1 | P12: =_xlfn.XLOOKUP($J12, items_clean!$A:$A, items_clean!$F:$F, "") -> 4.6 | Q12: =O12*P12 -> 4.6 | R12: =_xlfn.XLOOKUP(K12, recipe_cost!$A:$A, recipe_cost!$B:$B, "") -> 0.5667 | S12: =O12 * R12 -> 0.5667 | T12: =Q12-S12 -> 4.0333 | U12: =IF(Q12=0,"",T12/Q12) -> 0.87680435
A13: 12 | B13: ORD009 | C13: 45334.322 | D13: =INT(C13) -> 45334 | E13: =HOUR(C13) -> 7 | F13: {=_xlfn.IFS( E13<11,"Morning", E13<15,"Afternoon", TRUE,"Evening" )} -> Morning | G13: =TEXT(C13,"ddd") -> Mon | H13: Quinn | I13: out | J13: It023 | K13: =_xlfn.XLOOKUP($J13, items_clean!$A:$A, items_clean!$B:$B, "") -> SNK-SHC | L13: =_xlfn.XLOOKUP($J13, items_clean!$A:$A, items_clean!$C:$C, "") -> Sandwich Ham&Cheese | M13: =_xlfn.XLOOKUP($J13, items_clean!$A:$A, items_clean!$D:$D, "") -> Snacks | N13: =_xlfn.XLOOKUP($J13, items_clean!$A:$A, items_clean!$E:$E, "") -> N/A | O13: 1 | P13: =_xlfn.XLOOKUP($J13, items_clean!$A:$A, items_clean!$F:$F, "") -> 5.6 | Q13: =O13*P13 -> 5.6 | R13: =_xlfn.XLOOKUP(K13, recipe_cost!$A:$A, recipe_cost!$B:$B, "") -> 2.0105 | S13: =O13 * R13 -> 2.0105 | T13: =Q13-S13 -> 3.5895 | U13: =IF(Q13=0,"",T13/Q13) -> 0.64098214
... A467: 466 | B467: ORD436 | C467: 45339.708 | D467: =INT(C467) -> 45339 | E467: =HOUR(C467) -> 16 | F467: {=_xlfn.IFS( E467<11,"Morning", E467<15,"Afternoon", TRUE,"Evening" )} -> Evening | G467: =TEXT(C467,"ddd") -> Sat | H467: Jack | I467: out | J467: It002 | K467: =_xlfn.XLOOKUP($J467, items_clean!$A:$A, items_clean!$B:$B, "") -> HDR-CAP-LG | L467: =_xlfn.XLOOKUP($J467, items_clean!$A:$A, items_clean!$C:$C, "") -> Cappuccino | M467: =_xlfn.XLOOKUP($J467, items_clean!$A:$A, items_clean!$D:$D, "") -> Hot Drinks | N467: =_xlfn.XLOOKUP($J467, items_clean!$A:$A, items_clean!$E:$E, "") -> Large | O467: 1 | P467: =_xlfn.XLOOKUP($J467, items_clean!$A:$A, items_clean!$F:$F, "") -> 3.75 | Q467: =O467*P467 -> 3.75 | R467: =_xlfn.XLOOKUP(K467, recipe_cost!$A:$A, recipe_cost!$B:$B, "") -> 0.336 | S467: =O467 * R467 -> 0.336 | T467: =Q467-S467 -> 3.414 | U467: =IF(Q467=0,"",T467/Q467) -> 0.9104

Sheet operations_summary
A1: first_order_datetime | B1: last_order_datetime | C1: operating_days | D1: total_orders | E1: orders_per_day
A2: =MIN(sales_enriched!C:C) -> 45334.295 | B2: =MAX(sales_enriched!C:C) -> 45339.708 | C2: =COUNTA(_xlfn.UNIQUE(sales_enriched!D2:D467)) -> 6 | D2: =COUNT(sales_enriched!A2:A467) -> 466 | E2: =D2/C2 -> 77.666667
